dars/__init__.py
dars/__main__.py
dars/cli.py
dars/cli_config.py
dars/config.py
dars/datastructs.py
dars/defaults.py
dars/errors.py
dars/files/config.toml.example
dars/getdocsbyorgregionrequest.py
dars/getdocsbyreestrnumberrequest.py
dars/getnsirequest.py
dars/getpublicdocsrequest.py
dars/logger.py
dars/main.py
dars/models.py
dars/s3_repo.py
dars/templates/getdocsbyorgregionrequest.xml.j2
dars/templates/getdocsbyreestrnumberrequest.xml.j2
dars/templates/getnsirequest.xml.j2
dars/templates/getpublicdocsrequest.xml.j2
dars/templates/header.xml.j2
dars/templates/index.xml.j2
dars/utils.py
dars/xml.py
dars-2.1.0.dist-info/LICENSE
dars-2.1.0.dist-info/METADATA
dars-2.1.0.dist-info/WHEEL
dars-2.1.0.dist-info/entry_points.txt
dars-2.1.0.dist-info/RECORD
