Metadata-Version: 2.1
Name: dars
Version: 2.1.0
Summary: Клиент для сервиса отдачи информации и документов ЕИС
Home-page: https://gitverse.ru/gosplan-v2/dars
License: MIT
Keywords: ЕИС,закупки
Author: Nik M
Author-email: nn.mikh@yandex.ru
Requires-Python: >=3.10,<4.0
Classifier: License :: OSI Approved :: MIT License
Classifier: Operating System :: OS Independent
Classifier: Programming Language :: Python :: 3
Classifier: Programming Language :: Python :: 3.10
Classifier: Programming Language :: Python :: 3.11
Classifier: Programming Language :: Python :: 3.12
Requires-Dist: boto3 (>=1.34.84,<2.0.0)
Requires-Dist: jinja2 (>=3.1.3,<4.0.0)
Requires-Dist: pydantic-settings[toml] (>=2.2.1,<3.0.0)
Requires-Dist: requests (>=2.31.0,<3.0.0)
Requires-Dist: toml (>=0.10.2,<0.11.0)
Requires-Dist: typer (>=0.12.3,<0.13.0)
Project-URL: Repository, https://gitverse.ru/gosplan-v2/dars
